SerpScrap-0.13.0.data/scripts/install_chrome.sh
scrapcore/__init__.py
scrapcore/cachemanager.py
scrapcore/core.py
scrapcore/database.py
scrapcore/logger.py
scrapcore/parsing.py
scrapcore/result_writer.py
scrapcore/scraping.py
scrapcore/tools.py
scrapcore/user_agent.py
scrapcore/validator_config.py
scrapcore/parser/__init__.py
scrapcore/parser/google_parser.py
scrapcore/parser/parser.py
scrapcore/scraper/__init__.py
scrapcore/scraper/scrape_worker_factory.py
scrapcore/scraper/selenium.py
serpscrap/__init__.py
serpscrap/chrome_install.py
serpscrap/config.py
serpscrap/csv_writer.py
serpscrap/find_proxies.py
serpscrap/phantom_install.py
serpscrap/serpscrap.py
serpscrap/urlscrape.py
tests/__init__.py
tests/test_basic.py
SerpScrap-0.13.0.dist-info/LICENSE
SerpScrap-0.13.0.dist-info/METADATA
SerpScrap-0.13.0.dist-info/WHEEL
SerpScrap-0.13.0.dist-info/top_level.txt
SerpScrap-0.13.0.dist-info/RECORD
