Metadata-Version: 2.1
Name: SerpScrap
Version: 0.13.0
Summary: 
Home-page: https://github.com/ecoron/SerpScrap
Author: Ronald Schmidt
Author-email: ronald.schmidt@zu-web.de
License: MIT
Keywords: seo scraper ad-detection scraping keywords
Platform: UNKNOWN
Classifier: Development Status :: 4 - Beta
Classifier: Intended Audience :: Developers
Classifier: Topic :: Internet
Classifier: License :: OSI Approved :: MIT License
Classifier: Programming Language :: Python :: 3.4
Classifier: Programming Language :: Python :: 3.5
Classifier: Programming Language :: Python :: 3.6
Requires-Dist: PySocks (==1.7.0)
Requires-Dist: chardet (==3.0.4)
Requires-Dist: beautifulsoup4 (==4.8.0)
Requires-Dist: html2text (==2019.8.11)
Requires-Dist: lxml (==4.3.2)
Requires-Dist: sqlalchemy (==1.3.7)
Requires-Dist: selenium (==3.141.0)
Requires-Dist: cssselect (==1.1.0)
